truthound/__init__.py
truthound/_lazy.py
truthound/adapters.py
truthound/api.py
truthound/cache.py
truthound/cli.py
truthound/decorators.py
truthound/html_reporter.py
truthound/maskers.py
truthound/py.typed
truthound/report.py
truthound/scanners.py
truthound/schema.py
truthound/types.py
truthound/audit/__init__.py
truthound/audit/core.py
truthound/audit/filters.py
truthound/audit/formatters.py
truthound/audit/logger.py
truthound/audit/middleware.py
truthound/audit/storage.py
truthound/benchmark/__init__.py
truthound/benchmark/base.py
truthound/benchmark/comparison.py
truthound/benchmark/generators.py
truthound/benchmark/reporters.py
truthound/benchmark/runner.py
truthound/benchmark/scenarios.py
truthound/checkpoint/__init__.py
truthound/checkpoint/async_actions.py
truthound/checkpoint/async_base.py
truthound/checkpoint/async_checkpoint.py
truthound/checkpoint/async_runner.py
truthound/checkpoint/checkpoint.py
truthound/checkpoint/registry.py
truthound/checkpoint/runner.py
truthound/checkpoint/actions/__init__.py
truthound/checkpoint/actions/base.py
truthound/checkpoint/actions/custom.py
truthound/checkpoint/actions/discord_notify.py
truthound/checkpoint/actions/email_notify.py
truthound/checkpoint/actions/github_action.py
truthound/checkpoint/actions/opsgenie.py
truthound/checkpoint/actions/pagerduty.py
truthound/checkpoint/actions/slack_notify.py
truthound/checkpoint/actions/store_result.py
truthound/checkpoint/actions/teams_notify.py
truthound/checkpoint/actions/telegram_notify.py
truthound/checkpoint/actions/update_docs.py
truthound/checkpoint/actions/webhook.py
truthound/checkpoint/analytics/__init__.py
truthound/checkpoint/analytics/models.py
truthound/checkpoint/analytics/protocols.py
truthound/checkpoint/analytics/service.py
truthound/checkpoint/analytics/aggregations/__init__.py
truthound/checkpoint/analytics/aggregations/rollup.py
truthound/checkpoint/analytics/aggregations/time_bucket.py
truthound/checkpoint/analytics/analyzers/__init__.py
truthound-1.2.11.dist-info/METADATA
truthound-1.2.11.dist-info/WHEEL
truthound-1.2.11.dist-info/entry_points.txt
truthound-1.2.11.dist-info/licenses/LICENSE
truthound-1.2.11.dist-info/RECORD
