Metadata-Version: 2.4
Name: truthound
Version: 1.2.11
Summary: Zero-Configuration Data Quality Framework Powered by Polars
Project-URL: Homepage, https://github.com/seadonggyun4/Truthound
Project-URL: Repository, https://github.com/seadonggyun4/Truthound
Project-URL: Issues, https://github.com/seadonggyun4/Truthound/issues
Author-email: seadonggyun4 <seadonggyun4@gmail.com>
License-Expression: Apache-2.0
License-File: LICENSE
Keywords: data-masking,data-quality,data-validation,pii-detection,polars
Classifier: Development Status :: 3 - Alpha
Classifier: Intended Audience :: Developers
Classifier: Intended Audience :: Science/Research
Classifier: License :: OSI Approved :: Apache Software License
Classifier: Operating System :: OS Independent
Classifier: Programming Language :: Python :: 3
Classifier: Programming Language :: Python :: 3.11
Classifier: Programming Language :: Python :: 3.12
Classifier: Topic :: Scientific/Engineering
Classifier: Topic :: Software Development :: Libraries :: Python Modules
Classifier: Typing :: Typed
Requires-Python: >=3.11
Requires-Dist: polars>=1.0.0
Requires-Dist: pyyaml>=6.0.0
Requires-Dist: rich>=13.0.0
Requires-Dist: typer>=0.12.0
Provides-Extra: all
Requires-Dist: aiokafka>=0.9.0; extra == 'all'
Requires-Dist: azure-storage-blob>=12.0.0; extra == 'all'
Requires-Dist: boto3>=1.26.0; extra == 'all'
Requires-Dist: duckdb>=1.0.0; extra == 'all'
Requires-Dist: elasticsearch[async]>=8.0.0; extra == 'all'
Requires-Dist: google-cloud-storage>=2.0.0; extra == 'all'
Requires-Dist: jinja2>=3.0.0; extra == 'all'
Requires-Dist: motor>=3.0.0; extra == 'all'
Requires-Dist: pandas>=2.0.0; extra == 'all'
Requires-Dist: reflex>=0.4.0; extra == 'all'
Requires-Dist: scikit-learn>=1.3.0; extra == 'all'
Requires-Dist: scipy>=1.10.0; extra == 'all'
Requires-Dist: sqlalchemy>=2.0.0; extra == 'all'
Requires-Dist: weasyprint>=60.0; extra == 'all'
Requires-Dist: xxhash>=3.4.0; extra == 'all'
Provides-Extra: anomaly
Requires-Dist: scikit-learn>=1.3.0; extra == 'anomaly'
Requires-Dist: scipy>=1.10.0; extra == 'anomaly'
Provides-Extra: async-datasources
Requires-Dist: aiokafka>=0.9.0; extra == 'async-datasources'
Requires-Dist: elasticsearch[async]>=8.0.0; extra == 'async-datasources'
Requires-Dist: motor>=3.0.0; extra == 'async-datasources'
Provides-Extra: azure
Requires-Dist: azure-storage-blob>=12.0.0; extra == 'azure'
Provides-Extra: dashboard
Requires-Dist: reflex>=0.4.0; extra == 'dashboard'
Provides-Extra: database
Requires-Dist: sqlalchemy>=2.0.0; extra == 'database'
Provides-Extra: dev
Requires-Dist: mypy>=1.10.0; extra == 'dev'
Requires-Dist: pandas>=2.0.0; extra == 'dev'
Requires-Dist: pytest-asyncio>=0.23.0; extra == 'dev'
Requires-Dist: pytest-cov>=4.0.0; extra == 'dev'
Requires-Dist: pytest>=8.0.0; extra == 'dev'
Requires-Dist: ruff>=0.4.0; extra == 'dev'
Requires-Dist: scikit-learn>=1.3.0; extra == 'dev'
Requires-Dist: scipy>=1.10.0; extra == 'dev'
Provides-Extra: drift
Requires-Dist: scipy>=1.10.0; extra == 'drift'
Provides-Extra: duckdb
Requires-Dist: duckdb>=1.0.0; extra == 'duckdb'
Provides-Extra: elasticsearch
Requires-Dist: elasticsearch[async]>=8.0.0; extra == 'elasticsearch'
Provides-Extra: gcs
Requires-Dist: google-cloud-storage>=2.0.0; extra == 'gcs'
Provides-Extra: kafka
Requires-Dist: aiokafka>=0.9.0; extra == 'kafka'
Provides-Extra: mongodb
Requires-Dist: motor>=3.0.0; extra == 'mongodb'
Provides-Extra: nosql
Requires-Dist: elasticsearch[async]>=8.0.0; extra == 'nosql'
Requires-Dist: motor>=3.0.0; extra == 'nosql'
Provides-Extra: pdf
Requires-Dist: weasyprint>=60.0; extra == 'pdf'
Provides-Extra: perf
Requires-Dist: xxhash>=3.4.0; extra == 'perf'
Provides-Extra: reports
Requires-Dist: jinja2>=3.0.0; extra == 'reports'
Provides-Extra: s3
Requires-Dist: boto3>=1.26.0; extra == 's3'
Provides-Extra: stores
Requires-Dist: azure-storage-blob>=12.0.0; extra == 'stores'
Requires-Dist: boto3>=1.26.0; extra == 'stores'
Requires-Dist: google-cloud-storage>=2.0.0; extra == 'stores'
Requires-Dist: sqlalchemy>=2.0.0; extra == 'stores'
Provides-Extra: streaming
Requires-Dist: aiokafka>=0.9.0; extra == 'streaming'
